verification/__init__.py
verification/foo.py
verification-0.0.0.dist-info/LICENSE
verification-0.0.0.dist-info/METADATA
verification-0.0.0.dist-info/WHEEL
verification-0.0.0.dist-info/RECORD
