Metadata-Version: 2.1
Name: verification
Version: 0.0.0
Summary: Verification for post-training LLMs
Home-page: https://github.com/AlgoDistill/verification
Author: Florian Maas
Author-email: AlgoDistill@proton.me
Requires-Python: >=3.8,<4.0
Classifier: Programming Language :: Python :: 3
Classifier: Programming Language :: Python :: 3.8
Classifier: Programming Language :: Python :: 3.9
Classifier: Programming Language :: Python :: 3.10
Classifier: Programming Language :: Python :: 3.11
Classifier: Programming Language :: Python :: 3.12
Project-URL: Documentation, https://AlgoDistill.github.io/verification/
Project-URL: Repository, https://github.com/AlgoDistill/verification
